bureaucratese/__init__.py
bureaucratese/analyzer.py
bureaucratese/api.py
bureaucratese/bert_analyzer.py
bureaucratese/download_bert.py
bureaucratese/preprocess_embeddings.py
bureaucratese/web_api.py
bureaucratese/preprocessed/README.md
bureaucratese-0.1.0.dist-info/licenses/LICENSE
bureaucratese-0.1.0.dist-info/METADATA
bureaucratese-0.1.0.dist-info/WHEEL
bureaucratese-0.1.0.dist-info/top_level.txt
bureaucratese-0.1.0.dist-info/RECORD
