Metadata-Version: 2.4
Name: bureaucratese
Version: 0.1.0
Summary: A Python package for analyzing the density of Chinese official discourse in text
Home-page: https://github.com/adrian/bureaucratese
Author: Adrian
Author-email: 
Classifier: Programming Language :: Python :: 3
Classifier: License :: OSI Approved :: MIT License
Classifier: Operating System :: OS Independent
Classifier: Natural Language :: Chinese (Simplified)
Classifier: Topic :: Text Processing :: Linguistic
Classifier: Intended Audience :: Science/Research
Classifier: Development Status :: 4 - Beta
Requires-Python: >=3.6
License-File: LICENSE
Requires-Dist: pandas>=1.0.0
Requires-Dist: jieba>=0.42.1
Requires-Dist: torch>=1.7.0
Requires-Dist: transformers>=4.0.0
Requires-Dist: numpy>=1.19.0
Requires-Dist: tqdm>=4.45.0
Dynamic: author
Dynamic: classifier
Dynamic: description
Dynamic: description-content-type
Dynamic: home-page
Dynamic: license-file
Dynamic: requires-dist
Dynamic: requires-python
Dynamic: summary
